server_agents/__init__.py
server_agents/log.py
server_agents/server.py
server_agents/chat_bmm/__init__.py
server_agents/chat_bmm/core.py
server_agents/chat_bmm/log.py
server_agents/chat_bmm/server.py
server_agents/code/paper/server.py
server_agents/code/template/core.py
server_agents/code/template/manager.py
server_agents/code/template/utils/__init__.py
server_agents/code/template/utils/template_extract.py
server_agents/code/template/utils/vectorstore.py
server_agents/debug/core.py
server_agents/file/core.py
server_agents/file/file_manager.py
server_agents-0.1.1.dist-info/METADATA
server_agents-0.1.1.dist-info/WHEEL
server_agents-0.1.1.dist-info/top_level.txt
server_agents-0.1.1.dist-info/RECORD
